{
  "image": "2508.21513_On_the_Hardness_of_Learning_GNN-based_SAT_Solvers__page_11.png",
  "width": 2550,
  "height": 3300,
  "detections": [
    {
      "label": "text",
      "boxes": [
        [
          170.0,
          90.0,
          825.0,
          120.0
        ]
      ],
      "raw": "[[170, 90, 825, 120]]",
      "pixel_boxes": [
        [
          433,
          297,
          2105,
          396
        ]
      ]
    },
    {
      "label": "text",
      "boxes": [
        [
          170.0,
          123.0,
          825.0,
          153.0
        ]
      ],
      "raw": "[[170, 123, 825, 153]]",
      "pixel_boxes": [
        [
          433,
          406,
          2105,
          505
        ]
      ]
    },
    {
      "label": "text",
      "boxes": [
        [
          170.0,
          156.0,
          825.0,
          200.0
        ]
      ],
      "raw": "[[170, 156, 825, 200]]",
      "pixel_boxes": [
        [
          433,
          515,
          2105,
          660
        ]
      ]
    },
    {
      "label": "text",
      "boxes": [
        [
          170.0,
          203.0,
          825.0,
          233.0
        ]
      ],
      "raw": "[[170, 203, 825, 233]]",
      "pixel_boxes": [
        [
          433,
          670,
          2105,
          769
        ]
      ]
    },
    {
      "label": "text",
      "boxes": [
        [
          170.0,
          236.0,
          825.0,
          265.0
        ]
      ],
      "raw": "[[170, 236, 825, 265]]",
      "pixel_boxes": [
        [
          433,
          779,
          2105,
          875
        ]
      ]
    },
    {
      "label": "text",
      "boxes": [
        [
          170.0,
          269.0,
          825.0,
          298.0
        ]
      ],
      "raw": "[[170, 269, 825, 298]]",
      "pixel_boxes": [
        [
          433,
          888,
          2105,
          984
        ]
      ]
    },
    {
      "label": "text",
      "boxes": [
        [
          170.0,
          301.0,
          825.0,
          330.0
        ]
      ],
      "raw": "[[170, 301, 825, 330]]",
      "pixel_boxes": [
        [
          433,
          994,
          2105,
          1090
        ]
      ]
    },
    {
      "label": "text",
      "boxes": [
        [
          170.0,
          333.0,
          825.0,
          362.0
        ]
      ],
      "raw": "[[170, 333, 825, 362]]",
      "pixel_boxes": [
        [
          433,
          1100,
          2105,
          1195
        ]
      ]
    },
    {
      "label": "text",
      "boxes": [
        [
          170.0,
          366.0,
          825.0,
          408.0
        ]
      ],
      "raw": "[[170, 366, 825, 408]]",
      "pixel_boxes": [
        [
          433,
          1209,
          2105,
          1347
        ]
      ]
    },
    {
      "label": "text",
      "boxes": [
        [
          170.0,
          411.0,
          825.0,
          454.0
        ]
      ],
      "raw": "[[170, 411, 825, 454]]",
      "pixel_boxes": [
        [
          433,
          1357,
          2105,
          1499
        ]
      ]
    },
    {
      "label": "text",
      "boxes": [
        [
          170.0,
          458.0,
          825.0,
          500.0
        ]
      ],
      "raw": "[[170, 458, 825, 500]]",
      "pixel_boxes": [
        [
          433,
          1512,
          2105,
          1651
        ]
      ]
    },
    {
      "label": "text",
      "boxes": [
        [
          170.0,
          504.0,
          825.0,
          533.0
        ]
      ],
      "raw": "[[170, 504, 825, 533]]",
      "pixel_boxes": [
        [
          433,
          1664,
          2105,
          1760
        ]
      ]
    },
    {
      "label": "text",
      "boxes": [
        [
          170.0,
          537.0,
          825.0,
          578.0
        ]
      ],
      "raw": "[[170, 537, 825, 578]]",
      "pixel_boxes": [
        [
          433,
          1773,
          2105,
          1909
        ]
      ]
    },
    {
      "label": "text",
      "boxes": [
        [
          170.0,
          583.0,
          825.0,
          625.0
        ]
      ],
      "raw": "[[170, 583, 825, 625]]",
      "pixel_boxes": [
        [
          433,
          1925,
          2105,
          2064
        ]
      ]
    },
    {
      "label": "text",
      "boxes": [
        [
          170.0,
          629.0,
          825.0,
          671.0
        ]
      ],
      "raw": "[[170, 629, 825, 671]]",
      "pixel_boxes": [
        [
          433,
          2077,
          2105,
          2216
        ]
      ]
    },
    {
      "label": "text",
      "boxes": [
        [
          170.0,
          676.0,
          825.0,
          705.0
        ]
      ],
      "raw": "[[170, 676, 825, 705]]",
      "pixel_boxes": [
        [
          433,
          2233,
          2105,
          2328
        ]
      ]
    },
    {
      "label": "text",
      "boxes": [
        [
          170.0,
          709.0,
          825.0,
          750.0
        ]
      ],
      "raw": "[[170, 709, 825, 750]]",
      "pixel_boxes": [
        [
          433,
          2342,
          2105,
          2477
        ]
      ]
    },
    {
      "label": "text",
      "boxes": [
        [
          170.0,
          754.0,
          825.0,
          783.0
        ]
      ],
      "raw": "[[170, 754, 825, 783]]",
      "pixel_boxes": [
        [
          433,
          2490,
          2105,
          2586
        ]
      ]
    },
    {
      "label": "text",
      "boxes": [
        [
          170.0,
          787.0,
          825.0,
          816.0
        ]
      ],
      "raw": "[[170, 787, 825, 816]]",
      "pixel_boxes": [
        [
          433,
          2599,
          2105,
          2695
        ]
      ]
    },
    {
      "label": "text",
      "boxes": [
        [
          170.0,
          821.0,
          825.0,
          862.0
        ]
      ],
      "raw": "[[170, 821, 825, 862]]",
      "pixel_boxes": [
        [
          433,
          2712,
          2105,
          2847
        ]
      ]
    },
    {
      "label": "text",
      "boxes": [
        [
          170.0,
          867.0,
          825.0,
          909.0
        ]
      ],
      "raw": "[[170, 867, 825, 909]]",
      "pixel_boxes": [
        [
          433,
          2863,
          2105,
          3002
        ]
      ]
    }
  ]
}