{
  "image": "2510.15583_Attn-JGNN_Attention_Enhanced_Join-Graph_Neural_Net_page_12.png",
  "width": 2550,
  "height": 3300,
  "detections": [
    {
      "label": "table",
      "boxes": [
        [
          315.0,
          188.0,
          680.0,
          243.0
        ]
      ],
      "raw": "[[315, 188, 680, 243]]",
      "pixel_boxes": [
        [
          804,
          621,
          1735,
          802
        ]
      ]
    },
    {
      "label": "table_caption",
      "boxes": [
        [
          216.0,
          156.0,
          784.0,
          185.0
        ]
      ],
      "raw": "[[216, 156, 784, 185]]",
      "pixel_boxes": [
        [
          551,
          515,
          2001,
          611
        ]
      ]
    },
    {
      "label": "text",
      "boxes": [
        [
          217.0,
          275.0,
          785.0,
          367.0
        ]
      ],
      "raw": "[[217, 275, 785, 367]]",
      "pixel_boxes": [
        [
          553,
          908,
          2003,
          1212
        ]
      ]
    },
    {
      "label": "table",
      "boxes": [
        [
          328.0,
          440.0,
          668.0,
          510.0
        ]
      ],
      "raw": "[[328, 440, 668, 510]]",
      "pixel_boxes": [
        [
          837,
          1453,
          1705,
          1684
        ]
      ]
    },
    {
      "label": "table_caption",
      "boxes": [
        [
          216.0,
          408.0,
          784.0,
          438.0
        ]
      ],
      "raw": "[[216, 408, 784, 438]]",
      "pixel_boxes": [
        [
          551,
          1347,
          2001,
          1446
        ]
      ]
    },
    {
      "label": "table",
      "boxes": [
        [
          275.0,
          602.0,
          720.0,
          686.0
        ]
      ],
      "raw": "[[275, 602, 720, 686]]",
      "pixel_boxes": [
        [
          701,
          1988,
          1837,
          2266
        ]
      ]
    },
    {
      "label": "table_caption",
      "boxes": [
        [
          220.0,
          585.0,
          778.0,
          600.0
        ]
      ],
      "raw": "[[220, 585, 778, 600]]",
      "pixel_boxes": [
        [
          561,
          1932,
          1985,
          1981
        ]
      ]
    },
    {
      "label": "text",
      "boxes": [
        [
          217.0,
          718.0,
          785.0,
          840.0
        ]
      ],
      "raw": "[[217, 718, 785, 840]]",
      "pixel_boxes": [
        [
          553,
          2371,
          2003,
          2774
        ]
      ]
    }
  ]
}