{
  "image": "2505.16053_Learning_from_Algorithm_Feedback_One-Shot_SAT_Solv_page_12.png",
  "width": 2550,
  "height": 3300,
  "detections": [
    {
      "label": "sub_title",
      "boxes": [
        [
          174.0,
          88.0,
          338.0,
          105.0
        ]
      ],
      "raw": "[[174, 88, 338, 105]]",
      "pixel_boxes": [
        [
          444,
          290,
          862,
          346
        ]
      ]
    },
    {
      "label": "sub_title",
      "boxes": [
        [
          174.0,
          119.0,
          494.0,
          135.0
        ]
      ],
      "raw": "[[174, 119, 494, 135]]",
      "pixel_boxes": [
        [
          444,
          393,
          1260,
          445
        ]
      ]
    },
    {
      "label": "text",
      "boxes": [
        [
          173.0,
          143.0,
          825.0,
          201.0
        ]
      ],
      "raw": "[[173, 143, 825, 201]]",
      "pixel_boxes": [
        [
          441,
          472,
          2105,
          663
        ]
      ]
    },
    {
      "label": "equation",
      "boxes": [
        [
          377.0,
          205.0,
          823.0,
          264.0
        ]
      ],
      "raw": "[[377, 205, 823, 264]]",
      "pixel_boxes": [
        [
          962,
          677,
          2100,
          872
        ]
      ]
    },
    {
      "label": "sub_title",
      "boxes": [
        [
          174.0,
          277.0,
          450.0,
          293.0
        ]
      ],
      "raw": "[[174, 277, 450, 293]]",
      "pixel_boxes": [
        [
          444,
          915,
          1148,
          967
        ]
      ]
    },
    {
      "label": "text",
      "boxes": [
        [
          173.0,
          301.0,
          707.0,
          318.0
        ]
      ],
      "raw": "[[173, 301, 707, 318]]",
      "pixel_boxes": [
        [
          441,
          994,
          1804,
          1050
        ]
      ]
    },
    {
      "label": "equation",
      "boxes": [
        [
          387.0,
          323.0,
          823.0,
          342.0
        ]
      ],
      "raw": "[[387, 323, 823, 342]]",
      "pixel_boxes": [
        [
          987,
          1066,
          2100,
          1129
        ]
      ]
    },
    {
      "label": "text",
      "boxes": [
        [
          173.0,
          348.0,
          823.0,
          377.0
        ]
      ],
      "raw": "[[173, 348, 823, 377]]",
      "pixel_boxes": [
        [
          441,
          1149,
          2100,
          1245
        ]
      ]
    },
    {
      "label": "text",
      "boxes": [
        [
          173.0,
          381.0,
          823.0,
          439.0
        ]
      ],
      "raw": "[[173, 381, 823, 439]]",
      "pixel_boxes": [
        [
          441,
          1258,
          2100,
          1450
        ]
      ]
    },
    {
      "label": "equation",
      "boxes": [
        [
          372.0,
          443.0,
          823.0,
          485.0
        ]
      ],
      "raw": "[[372, 443, 823, 485]]",
      "pixel_boxes": [
        [
          949,
          1463,
          2100,
          1602
        ]
      ]
    },
    {
      "label": "text",
      "boxes": [
        [
          173.0,
          491.0,
          825.0,
          536.0
        ]
      ],
      "raw": "[[173, 491, 825, 536]]",
      "pixel_boxes": [
        [
          441,
          1621,
          2105,
          1770
        ]
      ]
    },
    {
      "label": "equation",
      "boxes": [
        [
          334.0,
          541.0,
          823.0,
          590.0
        ]
      ],
      "raw": "[[334, 541, 823, 590]]",
      "pixel_boxes": [
        [
          852,
          1787,
          2100,
          1948
        ]
      ]
    },
    {
      "label": "text",
      "boxes": [
        [
          173.0,
          595.0,
          825.0,
          696.0
        ]
      ],
      "raw": "[[173, 595, 825, 696]]",
      "pixel_boxes": [
        [
          441,
          1965,
          2105,
          2299
        ]
      ]
    },
    {
      "label": "equation",
      "boxes": [
        [
          390.0,
          701.0,
          823.0,
          720.0
        ]
      ],
      "raw": "[[390, 701, 823, 720]]",
      "pixel_boxes": [
        [
          995,
          2315,
          2100,
          2378
        ]
      ]
    },
    {
      "label": "text",
      "boxes": [
        [
          173.0,
          725.0,
          825.0,
          826.0
        ]
      ],
      "raw": "[[173, 725, 825, 826]]",
      "pixel_boxes": [
        [
          441,
          2394,
          2105,
          2728
        ]
      ]
    }
  ]
}