{
  "image": "2312.11547_A_unified_pre-training_and_adaptation_framework_fo_page_2.png",
  "width": 2550,
  "height": 3300,
  "detections": [
    {
      "label": "sub_title",
      "boxes": [
        [
          127.0,
          87.0,
          283.0,
          105.0
        ]
      ],
      "raw": "[[127, 87, 283, 105]]",
      "pixel_boxes": [
        [
          324,
          287,
          722,
          346
        ]
      ]
    },
    {
      "label": "text",
      "boxes": [
        [
          126.0,
          120.0,
          870.0,
          220.0
        ]
      ],
      "raw": "[[126, 120, 870, 220]]",
      "pixel_boxes": [
        [
          321,
          396,
          2220,
          726
        ]
      ]
    },
    {
      "label": "text",
      "boxes": [
        [
          126.0,
          221.0,
          871.0,
          453.0
        ]
      ],
      "raw": "[[126, 221, 871, 453]]",
      "pixel_boxes": [
        [
          321,
          730,
          2223,
          1496
        ]
      ]
    },
    {
      "label": "text",
      "boxes": [
        [
          126.0,
          454.0,
          871.0,
          619.0
        ]
      ],
      "raw": "[[126, 454, 871, 619]]",
      "pixel_boxes": [
        [
          321,
          1499,
          2223,
          2044
        ]
      ]
    },
    {
      "label": "text",
      "boxes": [
        [
          126.0,
          620.0,
          871.0,
          836.0
        ]
      ],
      "raw": "[[126, 620, 871, 836]]",
      "pixel_boxes": [
        [
          321,
          2048,
          2223,
          2761
        ]
      ]
    },
    {
      "label": "text",
      "boxes": [
        [
          127.0,
          838.0,
          871.0,
          937.0
        ]
      ],
      "raw": "[[127, 838, 871, 937]]",
      "pixel_boxes": [
        [
          324,
          2768,
          2223,
          3095
        ]
      ]
    }
  ]
}