{
  "image": "2408.15418_Understanding_GNNs_for_Boolean_Satisfiability_thro_page_10.png",
  "width": 2550,
  "height": 3300,
  "detections": [
    {
      "label": "sub_title",
      "boxes": [
        [
          85.0,
          104.0,
          312.0,
          121.0
        ]
      ],
      "raw": "[[85, 104, 312, 121]]",
      "pixel_boxes": [
        [
          216,
          343,
          796,
          399
        ]
      ]
    },
    {
      "label": "sub_title",
      "boxes": [
        [
          85.0,
          124.0,
          522.0,
          141.0
        ]
      ],
      "raw": "[[85, 124, 522, 141]]",
      "pixel_boxes": [
        [
          216,
          409,
          1332,
          465
        ]
      ]
    },
    {
      "label": "text",
      "boxes": [
        [
          85.0,
          143.0,
          911.0,
          172.0
        ]
      ],
      "raw": "[[85, 143, 911, 172]]",
      "pixel_boxes": [
        [
          216,
          472,
          2325,
          568
        ]
      ]
    },
    {
      "label": "text",
      "boxes": [
        [
          85.0,
          171.0,
          912.0,
          242.0
        ]
      ],
      "raw": "[[85, 171, 912, 242]]",
      "pixel_boxes": [
        [
          216,
          564,
          2327,
          799
        ]
      ]
    },
    {
      "label": "text",
      "boxes": [
        [
          85.0,
          240.0,
          912.0,
          269.0
        ]
      ],
      "raw": "[[85, 240, 912, 269]]",
      "pixel_boxes": [
        [
          216,
          792,
          2327,
          888
        ]
      ]
    },
    {
      "label": "equation",
      "boxes": [
        [
          316.0,
          317.0,
          680.0,
          448.0
        ]
      ],
      "raw": "[[316, 317, 680, 448]]",
      "pixel_boxes": [
        [
          806,
          1047,
          1735,
          1479
        ]
      ]
    },
    {
      "label": "text",
      "boxes": [
        [
          100.0,
          483.0,
          860.0,
          500.0
        ]
      ],
      "raw": "[[100, 483, 860, 500]]",
      "pixel_boxes": [
        [
          255,
          1595,
          2195,
          1651
        ]
      ]
    },
    {
      "label": "equation",
      "boxes": [
        [
          352.0,
          538.0,
          642.0,
          589.0
        ]
      ],
      "raw": "[[352, 538, 642, 589]]",
      "pixel_boxes": [
        [
          898,
          1777,
          1638,
          1945
        ]
      ]
    },
    {
      "label": "text",
      "boxes": [
        [
          85.0,
          624.0,
          912.0,
          683.0
        ]
      ],
      "raw": "[[85, 624, 912, 683]]",
      "pixel_boxes": [
        [
          216,
          2061,
          2327,
          2256
        ]
      ]
    },
    {
      "label": "equation",
      "boxes": [
        [
          328.0,
          737.0,
          667.0,
          773.0
        ]
      ],
      "raw": "[[328, 737, 667, 773]]",
      "pixel_boxes": [
        [
          837,
          2434,
          1702,
          2553
        ]
      ]
    },
    {
      "label": "text",
      "boxes": [
        [
          85.0,
          810.0,
          912.0,
          839.0
        ]
      ],
      "raw": "[[85, 810, 912, 839]]",
      "pixel_boxes": [
        [
          216,
          2675,
          2327,
          2771
        ]
      ]
    },
    {
      "label": "text",
      "boxes": [
        [
          85.0,
          839.0,
          912.0,
          867.0
        ]
      ],
      "raw": "[[85, 839, 912, 867]]",
      "pixel_boxes": [
        [
          216,
          2771,
          2327,
          2863
        ]
      ]
    },
    {
      "label": "text",
      "boxes": [
        [
          85.0,
          867.0,
          912.0,
          895.0
        ]
      ],
      "raw": "[[85, 867, 912, 895]]",
      "pixel_boxes": [
        [
          216,
          2863,
          2327,
          2956
        ]
      ]
    }
  ]
}