{
  "image": "2506.11057_STRCMP_Integrating_Graph_Structural_Priors_with_La_page_23.png",
  "width": 2550,
  "height": 3300,
  "detections": [
    {
      "label": "text",
      "boxes": [
        [
          172.0,
          90.0,
          823.0,
          118.0
        ]
      ],
      "raw": "[[172, 90, 823, 118]]",
      "pixel_boxes": [
        [
          439,
          297,
          2100,
          389
        ]
      ]
    },
    {
      "label": "equation",
      "boxes": [
        [
          434.0,
          125.0,
          822.0,
          165.0
        ]
      ],
      "raw": "[[434, 125, 822, 165]]",
      "pixel_boxes": [
        [
          1107,
          412,
          2098,
          545
        ]
      ]
    },
    {
      "label": "text",
      "boxes": [
        [
          173.0,
          174.0,
          216.0,
          187.0
        ]
      ],
      "raw": "[[173, 174, 216, 187]]",
      "pixel_boxes": [
        [
          441,
          574,
          551,
          617
        ]
      ]
    },
    {
      "label": "equation",
      "boxes": [
        [
          300.0,
          183.0,
          822.0,
          218.0
        ]
      ],
      "raw": "[[300, 183, 822, 218]]",
      "pixel_boxes": [
        [
          765,
          604,
          2098,
          720
        ]
      ]
    },
    {
      "label": "sub_title",
      "boxes": [
        [
          173.0,
          235.0,
          295.0,
          252.0
        ]
      ],
      "raw": "[[173, 235, 295, 252]]",
      "pixel_boxes": [
        [
          441,
          776,
          753,
          832
        ]
      ]
    },
    {
      "label": "text",
      "boxes": [
        [
          173.0,
          265.0,
          824.0,
          363.0
        ]
      ],
      "raw": "[[173, 265, 824, 363]]",
      "pixel_boxes": [
        [
          441,
          875,
          2103,
          1199
        ]
      ]
    },
    {
      "label": "text",
      "boxes": [
        [
          174.0,
          368.0,
          824.0,
          466.0
        ]
      ],
      "raw": "[[174, 368, 824, 466]]",
      "pixel_boxes": [
        [
          444,
          1215,
          2103,
          1539
        ]
      ]
    },
    {
      "label": "text",
      "boxes": [
        [
          174.0,
          472.0,
          825.0,
          585.0
        ]
      ],
      "raw": "[[174, 472, 825, 585]]",
      "pixel_boxes": [
        [
          444,
          1559,
          2105,
          1932
        ]
      ]
    }
  ]
}