{
  "image": "2506.11057_STRCMP_Integrating_Graph_Structural_Priors_with_La_page_3.png",
  "width": 2550,
  "height": 3300,
  "detections": [
    {
      "label": "text",
      "boxes": [
        [
          174.0,
          91.0,
          824.0,
          147.0
        ]
      ],
      "raw": "[[174, 91, 824, 147]]",
      "pixel_boxes": [
        [
          444,
          300,
          2103,
          485
        ]
      ]
    },
    {
      "label": "sub_title",
      "boxes": [
        [
          174.0,
          164.0,
          320.0,
          181.0
        ]
      ],
      "raw": "[[174, 164, 320, 181]]",
      "pixel_boxes": [
        [
          444,
          541,
          816,
          597
        ]
      ]
    },
    {
      "label": "text",
      "boxes": [
        [
          174.0,
          194.0,
          825.0,
          459.0
        ]
      ],
      "raw": "[[174, 194, 825, 459]]",
      "pixel_boxes": [
        [
          444,
          640,
          2105,
          1516
        ]
      ]
    },
    {
      "label": "text",
      "boxes": [
        [
          174.0,
          464.0,
          825.0,
          795.0
        ]
      ],
      "raw": "[[174, 464, 825, 795]]",
      "pixel_boxes": [
        [
          444,
          1532,
          2105,
          2626
        ]
      ]
    },
    {
      "label": "sub_title",
      "boxes": [
        [
          175.0,
          813.0,
          365.0,
          830.0
        ]
      ],
      "raw": "[[175, 813, 365, 830]]",
      "pixel_boxes": [
        [
          446,
          2685,
          931,
          2741
        ]
      ]
    },
    {
      "label": "text",
      "boxes": [
        [
          175.0,
          843.0,
          824.0,
          886.0
        ]
      ],
      "raw": "[[175, 843, 824, 886]]",
      "pixel_boxes": [
        [
          446,
          2784,
          2103,
          2926
        ]
      ]
    },
    {
      "label": "equation",
      "boxes": [
        [
          415.0,
          890.0,
          822.0,
          911.0
        ]
      ],
      "raw": "[[415, 890, 822, 911]]",
      "pixel_boxes": [
        [
          1059,
          2939,
          2098,
          3009
        ]
      ]
    }
  ]
}