{
  "image": "2205.04423_Graph_Neural_Networks_for_Propositional_Model_Coun_page_6.png",
  "width": 2550,
  "height": 3300,
  "detections": [
    {
      "label": "text",
      "boxes": [
        [
          217.0,
          145.0,
          786.0,
          266.0
        ]
      ],
      "raw": "[[217, 145, 786, 266]]",
      "pixel_boxes": [
        [
          553,
          478,
          2006,
          878
        ]
      ]
    },
    {
      "label": "sub_title",
      "boxes": [
        [
          217.0,
          300.0,
          542.0,
          316.0
        ]
      ],
      "raw": "[[217, 300, 542, 316]]",
      "pixel_boxes": [
        [
          553,
          990,
          1383,
          1043
        ]
      ]
    },
    {
      "label": "text",
      "boxes": [
        [
          218.0,
          338.0,
          785.0,
          413.0
        ]
      ],
      "raw": "[[218, 338, 785, 413]]",
      "pixel_boxes": [
        [
          556,
          1116,
          2003,
          1364
        ]
      ]
    },
    {
      "label": "text",
      "boxes": [
        [
          218.0,
          416.0,
          785.0,
          476.0
        ]
      ],
      "raw": "[[218, 416, 785, 476]]",
      "pixel_boxes": [
        [
          556,
          1374,
          2003,
          1572
        ]
      ]
    },
    {
      "label": "text",
      "boxes": [
        [
          218.0,
          479.0,
          785.0,
          573.0
        ]
      ],
      "raw": "[[218, 479, 785, 573]]",
      "pixel_boxes": [
        [
          556,
          1582,
          2003,
          1892
        ]
      ]
    },
    {
      "label": "text",
      "boxes": [
        [
          217.0,
          575.0,
          785.0,
          768.0
        ]
      ],
      "raw": "[[217, 575, 785, 768]]",
      "pixel_boxes": [
        [
          553,
          1899,
          2003,
          2536
        ]
      ]
    },
    {
      "label": "equation",
      "boxes": [
        [
          246.0,
          800.0,
          783.0,
          843.0
        ]
      ],
      "raw": "[[246, 800, 783, 843]]",
      "pixel_boxes": [
        [
          627,
          2642,
          1998,
          2784
        ]
      ]
    }
  ]
}